README.md
setup.py
pulumi_prodvana/__init__.py
pulumi_prodvana/_inputs.py
pulumi_prodvana/_utilities.py
pulumi_prodvana/application.py
pulumi_prodvana/container_registry.py
pulumi_prodvana/ecr_registry.py
pulumi_prodvana/get_application.py
pulumi_prodvana/get_k8s_runtime.py
pulumi_prodvana/get_release_channel.py
pulumi_prodvana/k8s_runtime.py
pulumi_prodvana/managed_k8s_runtime.py
pulumi_prodvana/outputs.py
pulumi_prodvana/provider.py
pulumi_prodvana/pulumi-plugin.json
pulumi_prodvana/py.typed
pulumi_prodvana/release_channel.py
pulumi_prodvana/runtime_link.py
pulumi_prodvana.egg-info/PKG-INFO
pulumi_prodvana.egg-info/SOURCES.txt
pulumi_prodvana.egg-info/dependency_links.txt
pulumi_prodvana.egg-info/not-zip-safe
pulumi_prodvana.egg-info/requires.txt
pulumi_prodvana.egg-info/top_level.txt
pulumi_prodvana/config/__init__.py
pulumi_prodvana/config/vars.py