Metadata-Version: 2.1
Name: pulumi-prodvana
Version: 0.1.20
Summary: A Pulumi package for creating and managing Prodvana cloud resources.
Home-page: https://prodvana.io
License: Apache-2.0
Project-URL: Repository, https://github.com/prodvana/pulumi-prodvana
Keywords: pulumi prodvana category/cloud category/infrastructure
Platform: UNKNOWN
Requires-Python: >=3.8
